book_post_generator/douban.py
book_post_generator/main.py
book_post_generator/spinner.py
book_post_generator/zhipu.py
book_post_generator-0.1.3.dist-info/LICENSE
book_post_generator-0.1.3.dist-info/METADATA
book_post_generator-0.1.3.dist-info/WHEEL
book_post_generator-0.1.3.dist-info/entry_points.txt
book_post_generator-0.1.3.dist-info/RECORD
