Metadata-Version: 2.1
Name: book-post-generator
Version: 0.1.3
Summary: A CLI tool to generate promotional book content using Douban and Zhipu APIs
License: MIT
Keywords: python,douban,zhipuai,xiaohongshu
Author: Zhongwei
Author-email: lizhongwei.nkcs@gmail.com
Requires-Python: >=3.9,<3.12
Classifier: License :: OSI Approved :: MIT License
Classifier: Programming Language :: Python :: 3
Classifier: Programming Language :: Python :: 3.9
Classifier: Programming Language :: Python :: 3.10
Classifier: Programming Language :: Python :: 3.11
Requires-Dist: configparser (>=6.0.0,<7.0.0)
Requires-Dist: fire (>=0.5.0,<0.6.0)
Requires-Dist: requests (>=2.31.0,<3.0.0)
Requires-Dist: zhipuai (>=1.0.7,<2.0.0)
